{
	"name": "Член. Горловой минет.",
	"description": "Какая-то неправильная гастроскопия.",
	"usage": "other",
	"category": "Erp",
	"distance_allowed": 0,
	"message": [
		"%USER% вводит поглубже в свою глотку член %TARGET%.",
		"%USER% давится членом %TARGET%.",
		"%USER% заглатывает член %TARGET% по самые гланды.",
		"%USER% показывает чудеса горлового минета для %TARGET%."
	],
	"sound_use": 1,
	"sound_range": 3,
	"interaction_requires": [
		"self_mouth"
	],
	"target_required_parts": [
		"penis"
	],
	"color": "purple",
	"user_arousal": 7,
	"target_arousal": 10,
	"user_pleasure": 7,
	"target_pleasure": 10,
	"lewd": 1,
	"sound_possible":[
		"modular_skyrat/modules/modular_items/lewd_items/sounds/oral1.ogg",
		"modular_skyrat/modules/modular_items/lewd_items/sounds/oral2.ogg"
	]
}
